Metadata-Version: 1.0
Name: zope.pypisupport
Version: 0.1.1
Summary: Python Package Index (PyPI) role management tools
Home-page: http://pypi.python.org/pypi/zope.pypisupport
Author: Zope Corporation and Contributors
Author-email: zope-dev@zope.org
License: ZPL 2.1
Keywords: pypi console tools
Platform: UNKNOWN
Classifier: Development Status :: 4 - Beta
Classifier: Environment :: Console
Classifier: Intended Audience :: Developers
Classifier: License :: OSI Approved :: Zope Public License
Classifier: Programming Language :: Python
Classifier: Natural Language :: English
Classifier: Operating System :: OS Independent
Classifier: Topic :: Internet :: WWW/HTTP
